asciifier/.DS_Store
asciifier/AsciiArt.py
asciifier/__init__.py
asciifier/_constants.py
asciifier-1.0.1.dist-info/LICENSE
asciifier-1.0.1.dist-info/METADATA
asciifier-1.0.1.dist-info/WHEEL
asciifier-1.0.1.dist-info/RECORD
